LICENSE.txt
MANIFEST.in
README.rst
setup.cfg
setup.py
Webifi.egg-info/PKG-INFO
Webifi.egg-info/SOURCES.txt
Webifi.egg-info/dependency_links.txt
Webifi.egg-info/requires.txt
Webifi.egg-info/top_level.txt
Webifi_p27/Webifi_p27.py
Webifi_p27/__init__.py
Webifi_p3/Webifi_p3.py
Webifi_p3/__init__.py